sunsuku/__init__.py
sunsuku/base.py
sunsuku/claude_api.py
sunsuku/exceptions.py
sunsuku/gemini_api.py
sunsuku/gpt_api.py
sunsuku/sunsuku.py
sunsuku-0.1.2.dist-info/METADATA
sunsuku-0.1.2.dist-info/WHEEL
sunsuku-0.1.2.dist-info/RECORD
