Metadata-Version: 2.1
Name: sunsuku
Version: 0.1.2
Summary: LLMAI API Wrapper
License: MIT
Author: hideyuki-ogawa
Author-email: hogawa098@gmail.com
Requires-Python: >=3.10,<4.0
Classifier: License :: OSI Approved :: MIT License
Classifier: Programming Language :: Python :: 3
Classifier: Programming Language :: Python :: 3.10
Classifier: Programming Language :: Python :: 3.11
Classifier: Programming Language :: Python :: 3.12
Requires-Dist: anthropic (>=0.34.2,<0.35.0)
Requires-Dist: google-generativeai (>=0.8.0,<0.9.0)
Requires-Dist: openai (>=1.44.1,<2.0.0)
